jsonschema_schema_validator/__init__.py
jsonschema_schema_validator/__main__.py
jsonschema_schema_validator/exceptions.py
jsonschema_schema_validator/validator.py
jsonschema_schema_validator-0.1.0.dist-info/METADATA
jsonschema_schema_validator-0.1.0.dist-info/WHEEL
jsonschema_schema_validator-0.1.0.dist-info/top_level.txt
jsonschema_schema_validator-0.1.0.dist-info/RECORD
