Metadata-Version: 2.1
Name: jsonschema-schema-validator
Version: 0.1.0
Author-email: Stephen Finucane <stephen@that.guru>
License: BSD-3-Clause
Requires-Python: >=3.9
